AssetVendor-0.0.2.dist-info/METADATA
AssetVendor-0.0.2.dist-info/RECORD
AssetVendor-0.0.2.dist-info/WHEEL
AssetVendor-0.0.2.dist-info/entry_points.txt
AssetVendor-0.0.2.dist-info/top_level.txt
assetvendor/__init__.py
assetvendor/__main__.py
assetvendor/cli.py
assetvendor/config.py
assetvendor/npm.py
assetvendor/range_parser.py
assetvendor/yaml.py
assetvendor/commands/__init__.py
assetvendor/commands/base.py
assetvendor/commands/check.py
assetvendor/commands/init.py
assetvendor/commands/install.py
