Metadata-Version: 2.1
Name: AssetVendor
Version: 0.0.2
Summary: A simple dealer of node packages...
Home-page: https://github.com/rpkilby/AssetVendor
Author: Ryan P Kilby
License: BSD
Platform: UNKNOWN
Classifier: Development Status :: 2 - Pre-Alpha
Classifier: Environment :: Web Environment
Classifier: Intended Audience :: Developers
Classifier: License :: OSI Approved :: BSD License
Classifier: Operating System :: OS Independent
Classifier: Programming Language :: Python
Classifier: Programming Language :: Python :: 3
Classifier: Programming Language :: Python :: 3.4
Classifier: Programming Language :: Python :: 3.5
Classifier: Programming Language :: Python :: 3.6
Classifier: Programming Language :: Python :: 3 :: Only
Classifier: Topic :: Internet :: WWW/HTTP
Classifier: Topic :: Software Development :: Libraries :: Python Modules
Provides-Extra: packaging
Provides-Extra: dev
Provides-Extra: yaml
Provides-Extra: dev
Requires-Dist: tox; extra == 'dev'
Requires-Dist: tox-venv; extra == 'dev'
Requires-Dist: ipython; extra == 'dev'
Provides-Extra: packaging
Requires-Dist: packaging; extra == 'packaging'
Provides-Extra: yaml
Requires-Dist: pyyaml; extra == 'yaml'
